plover_retro_text_transform/__init__.py
plover_retro_text_transform-0.1.1.dist-info/DESCRIPTION.rst
plover_retro_text_transform-0.1.1.dist-info/METADATA
plover_retro_text_transform-0.1.1.dist-info/RECORD
plover_retro_text_transform-0.1.1.dist-info/WHEEL
plover_retro_text_transform-0.1.1.dist-info/entry_points.txt
plover_retro_text_transform-0.1.1.dist-info/metadata.json
plover_retro_text_transform-0.1.1.dist-info/top_level.txt
plover_retro_text_transform-0.1.1.dist-info/zip-safe
